{"v":4,"entries":{"sequence-diagram--documentation":{"id":"sequence-diagram--documentation","title":"Sequence Diagram","name":"Documentation","importPath":"./src/stories/sequence-diagram/Sequence-Diagram.stories.ts","type":"docs","tags":["autodocs","sequence","diagram","docs"],"storiesImports":[]},"sequence-diagram--default":{"type":"story","id":"sequence-diagram--default","name":"Default","title":"Sequence Diagram","importPath":"./src/stories/sequence-diagram/Sequence-Diagram.stories.ts","tags":["autodocs","sequence","diagram","story"]}}}
